fixtures/__init__.py
fixtures/inject_fixtures.py
lain_sdk/__init__.py
lain_sdk/lain_yaml.py
lain_sdk/mydocker.py
lain_sdk/util.py
lain_sdk/yaml/__init__.py
lain_sdk/yaml/conf.py
lain_sdk/yaml/lain_user_config.py
lain_sdk/yaml/parser.py
lain_sdk/yaml/util.py
lain_sdk/yaml/watch.py
lain_sdk/yaml/templates/build_dockerfile.j2
lain_sdk/yaml/templates/meta_dockerfile.j2
lain_sdk/yaml/templates/release_dockerfile.j2
lain_sdk/yaml/validator/__init__.py
lain_sdk/yaml/validator/schema.py
lain_sdk-2.3.7.data/scripts/lain_release
lain_sdk-2.3.7.dist-info/DESCRIPTION.rst
lain_sdk-2.3.7.dist-info/METADATA
lain_sdk-2.3.7.dist-info/RECORD
lain_sdk-2.3.7.dist-info/WHEEL
lain_sdk-2.3.7.dist-info/metadata.json
lain_sdk-2.3.7.dist-info/top_level.txt
tests/__init__.py
tests/conftest.py
tests/test_lain_conf.py
tests/test_lain_sdk_parser.py
tests/test_lain_sdk_validator.py
tests/test_lain_user_config.py
tests/test_lain_yaml.py
