Metadata-Version: 2.0
Name: lain-sdk
Version: 2.3.7
Summary: UNKNOWN
Home-page: UNKNOWN
Author: UNKNOWN
Author-email: UNKNOWN
License: UNKNOWN
Platform: UNKNOWN
Requires-Dist: Jinja2 (==2.7.3)
Requires-Dist: PyYAML (==3.11)
Requires-Dist: docker (==2.1.0)
Requires-Dist: enum34 (==1.0.4)
Requires-Dist: jsonschema (==2.5.1)
Requires-Dist: mock (==1.0.1)
Requires-Dist: pytest
Requires-Dist: requests (==2.6.0)
Requires-Dist: websocket-client (==0.32.0)
